libfinder/__init__.py
libfinder/main.py
libfinder-0.1.7.dist-info/LICENSE
libfinder-0.1.7.dist-info/METADATA
libfinder-0.1.7.dist-info/WHEEL
libfinder-0.1.7.dist-info/top_level.txt
libfinder-0.1.7.dist-info/RECORD
