Metadata-Version: 2.2
Name: libfinder
Version: 0.1.7
Summary: A simple package to check if a Python library is installed in a Jupyter notebook.
Home-page: https://github.com/KaushiML3/libfinder
Author: Kaushi Gihan
Author-email: kaushigihanml@gmail.com
Classifier: Programming Language :: Python :: 3
Classifier: License :: OSI Approved :: MIT License
Classifier: Operating System :: OS Independent
Requires-Python: >=3.6
License-File: LICENSE
Requires-Dist: pandas
Requires-Dist: numpy
Requires-Dist: ipython
Dynamic: author
Dynamic: author-email
Dynamic: classifier
Dynamic: description
Dynamic: description-content-type
Dynamic: home-page
Dynamic: requires-dist
Dynamic: requires-python
Dynamic: summary
